README.rst
setup.cfg
setup.py
liable/__init__.py
liable/arboretum.py
liable/catalog.py
liable/file_system.py
liable/fixtures.py
liable/liable.py
liable/modules.py
liable/namespaces.py
liable/parameters.py
liable/strategies.py
liable/strings.py
liable/test_cases.py
liable/types.py
liable/utils.py
liable/validators.py
liable.egg-info/PKG-INFO
liable.egg-info/SOURCES.txt
liable.egg-info/dependency_links.txt
liable.egg-info/entry_points.txt
liable.egg-info/requires.txt
liable.egg-info/top_level.txt
liable/annotator/__init__.py
liable/annotator/annotations.py
liable/annotator/base.py
liable/annotator/detectors.py
liable/annotator/utils.py
liable/functions/__init__.py
liable/functions/detectors.py
liable/functions/utils.py
tests/fixtures/__init__.py
tests/fixtures/ast.py
tests/fixtures/collections.py
tests/fixtures/inflect.py
tests/fixtures/inspect.py
tests/fixtures/liable.py
tests/fixtures/types.py
tests/fixtures/utils.py
tests/liable/__init__.py
tests/liable/test_arboretum.py
tests/liable/test_catalog.py
tests/liable/test_file_system.py
tests/liable/test_fixtures.py
tests/liable/test_liable.py
tests/liable/test_modules.py
tests/liable/test_namespaces.py
tests/liable/test_parameters.py
tests/liable/test_strategies.py
tests/liable/test_strings.py
tests/liable/test_test_cases.py
tests/liable/test_utils.py
tests/liable/test_validators.py
tests/liable/annotator/__init__.py
tests/liable/annotator/test_detectors.py
tests/liable/annotator/test_utils.py
tests/liable/functions/__init__.py
tests/liable/functions/test_detectors.py
tests/liable/functions/test_utils.py
tests/strategies/__init__.py
tests/strategies/ast.py
tests/strategies/collections.py
tests/strategies/inflect.py
tests/strategies/inspect.py
tests/strategies/liable.py
tests/strategies/types.py
tests/strategies/utils.py