Metadata-Version: 1.1
Name: liable
Version: 0.0.3
Summary: Auto-tests generator.
Home-page: https://github.com/lycantropos/liable/
Author: Azat Ibrakov
Author-email: azatibrakov@gmail.com
License: UNKNOWN
Download-URL: https://github.com/lycantropos/liable/archive/master.zip
Platform: UNKNOWN
